rlp_tools_gui/__init__.py
rlp_tools_gui/__main__.pyw
rlp_tools_gui/form.py
rlp_tools_gui/form.ui
rlp_tools_gui/icon.ico
rlp_tools_gui-0.12.dist-info/METADATA
rlp_tools_gui-0.12.dist-info/RECORD
rlp_tools_gui-0.12.dist-info/WHEEL
rlp_tools_gui-0.12.dist-info/top_level.txt
